LICENSE
README.md
setup.cfg
setup.py
versioneer.py
asreview_notes_export.egg-info/PKG-INFO
asreview_notes_export.egg-info/SOURCES.txt
asreview_notes_export.egg-info/dependency_links.txt
asreview_notes_export.egg-info/entry_points.txt
asreview_notes_export.egg-info/requires.txt
asreview_notes_export.egg-info/top_level.txt
asreviewcontrib/notes_export/__init__.py
asreviewcontrib/notes_export/_version.py
asreviewcontrib/notes_export/entrypoint.py
asreviewcontrib/notes_export/notes_export.py