Metadata-Version: 2.1
Name: asreview-notes-export
Version: 0.0.7
Summary: ASReview notes export extension
Home-page: https://github.com/rohitgarud/asreview-notes-export
Author: Rohit Garud
Author-email: rohit.garuda1992@gmail.com
Project-URL: Bug Reports, https://github.com/rohitgarud/asreview-notes-export/issues
Project-URL: Source, https://github.com/rohitgarud/asreview-notes-export
Keywords: asreview notes export
Classifier: Development Status :: 3 - Alpha
Classifier: License :: OSI Approved :: Apache Software License
Classifier: Programming Language :: Python :: 3.7
Classifier: Programming Language :: Python :: 3.8
Classifier: Programming Language :: Python :: 3.9
Classifier: Programming Language :: Python :: 3.10
License-File: LICENSE
